hello_web/__init__.py
hello_web/main.py
hello_web-0.1.1.dist-info/METADATA
hello_web-0.1.1.dist-info/WHEEL
hello_web-0.1.1.dist-info/entry_points.txt
hello_web-0.1.1.dist-info/top_level.txt
hello_web-0.1.1.dist-info/RECORD
