Metadata-Version: 2.4
Name: hello_web
Version: 0.1.1
Summary: A flask demo return hello
Author-email: Your Name <your.email@example.com>
License: MIT
Requires-Python: >=3.12
Requires-Dist: flask>=3.1.1
